{
    "id": "ELECTRODE",
    "formId": "ELECTRODE",
    "dexNr": 101,
    "generation": 1,
    "names": {
        "English": "Electrode",
        "German": "Lektrobal",
        "French": "\u00c9lectrode",
        "Italian": "Electrode",
        "Japanese": "\u30de\u30eb\u30de\u30a4\u30f3",
        "Korean": "\ubd90\ubcfc",
        "Spanish": "Electrode"
    },
    "stats": {
        "stamina": 155,
        "attack": 173,
        "defense": 173
    },
    "primaryType": {
        "type": "POKEMON_TYPE_ELECTRIC",
        "names": {
            "English": "Electric",
            "German": "Elektro",
            "French": "\u00c9lectrik",
            "Italian": "Elettro",
            "Japanese": "\u3067\u3093\u304d",
            "Korean": "\uc804\uae30",
            "Spanish": "El\u00e9ctrico"
        }
    },
    "secondaryType": null,
    "pokemonClass": null,
    "quickMoves": {
        "SPARK_FAST": {
            "id": "SPARK_FAST",
            "power": 4,
            "energy": 6,
            "durationMs": 500,
            "type": {
                "type": "POKEMON_TYPE_ELECTRIC",
                "names": {
                    "English": "Electric",
                    "German": "Elektro",
                    "French": "\u00c9lectrik",
                    "Italian": "Elettro",
                    "Japanese": "\u3067\u3093\u304d",
                    "Korean": "\uc804\uae30",
                    "Spanish": "El\u00e9ctrico"
                }
            },
            "names": {
                "English": "Spark",
                "German": "Funkensprung",
                "French": "\u00c9tincelle",
                "Italian": "Scintilla",
                "Japanese": "\u30b9\u30d1\u30fc\u30af",
                "Korean": "\uc2a4\ud30c\ud06c",
                "Spanish": "Chispa"
            },
            "combat": {
                "energy": 7,
                "power": 5,
                "turns": 2,
                "buffs": null
            }
        },
        "VOLT_SWITCH_FAST": {
            "id": "VOLT_SWITCH_FAST",
            "power": 13,
            "energy": 20,
            "durationMs": 1500,
            "type": {
                "type": "POKEMON_TYPE_ELECTRIC",
                "names": {
                    "English": "Electric",
                    "German": "Elektro",
                    "French": "\u00c9lectrik",
                    "Italian": "Elettro",
                    "Japanese": "\u3067\u3093\u304d",
                    "Korean": "\uc804\uae30",
                    "Spanish": "El\u00e9ctrico"
                }
            },
            "names": {
                "English": "Volt Switch",
                "German": "Voltwechsel",
                "French": "Change \u00c9clair",
                "Italian": "Invertivolt",
                "Japanese": "\u30dc\u30eb\u30c8\u30c1\u30a7\u30f3\u30b8",
                "Korean": "\ubcfc\ud2b8\uccb4\uc778\uc9c0",
                "Spanish": "Voltiocambio"
            },
            "combat": {
                "energy": 16,
                "power": 14,
                "turns": 4,
                "buffs": null
            }
        }
    },
    "cinematicMoves": {
        "DISCHARGE": {
            "id": "DISCHARGE",
            "power": 65,
            "energy": -33,
            "durationMs": 2500,
            "type": {
                "type": "POKEMON_TYPE_ELECTRIC",
                "names": {
                    "English": "Electric",
                    "German": "Elektro",
                    "French": "\u00c9lectrik",
                    "Italian": "Elettro",
                    "Japanese": "\u3067\u3093\u304d",
                    "Korean": "\uc804\uae30",
                    "Spanish": "El\u00e9ctrico"
                }
            },
            "names": {
                "English": "Discharge",
                "German": "Ladungssto\u00df",
                "French": "Coup d\u2019Jus",
                "Italian": "Scarica",
                "Japanese": "\u307b\u3046\u3067\u3093",
                "Korean": "\ubc29\uc804",
                "Spanish": "Chispazo"
            },
            "combat": {
                "energy": -40,
                "power": 55,
                "turns": 1,
                "buffs": null
            }
        },
        "THUNDERBOLT": {
            "id": "THUNDERBOLT",
            "power": 80,
            "energy": -50,
            "durationMs": 2500,
            "type": {
                "type": "POKEMON_TYPE_ELECTRIC",
                "names": {
                    "English": "Electric",
                    "German": "Elektro",
                    "French": "\u00c9lectrik",
                    "Italian": "Elettro",
                    "Japanese": "\u3067\u3093\u304d",
                    "Korean": "\uc804\uae30",
                    "Spanish": "El\u00e9ctrico"
                }
            },
            "names": {
                "English": "Thunderbolt",
                "German": "Donnerblitz",
                "French": "Tonnerre",
                "Italian": "Fulmine",
                "Japanese": "\uff11\uff10\u307e\u3093\u30dc\u30eb\u30c8",
                "Korean": "10\ub9cc\ubcfc\ud2b8",
                "Spanish": "Rayo"
            },
            "combat": {
                "energy": -55,
                "power": 90,
                "turns": 1,
                "buffs": null
            }
        },
        "HYPER_BEAM": {
            "id": "HYPER_BEAM",
            "power": 150,
            "energy": -100,
            "durationMs": 4000,
            "type": {
                "type": "POKEMON_TYPE_NORMAL",
                "names": {
                    "English": "Normal",
                    "German": "Normal",
                    "French": "Normal",
                    "Italian": "Normale",
                    "Japanese": "\u30ce\u30fc\u30de\u30eb",
                    "Korean": "\ub178\ub9d0",
                    "Spanish": "Normal"
                }
            },
            "names": {
                "English": "Hyper Beam",
                "German": "Hyperstrahl",
                "French": "Ultralaser",
                "Italian": "Iper Raggio",
                "Japanese": "\u306f\u304b\u3044\u3053\u3046\u305b\u3093",
                "Korean": "\ud30c\uad34\uad11\uc120",
                "Spanish": "Hiperrayo"
            },
            "combat": {
                "energy": -80,
                "power": 150,
                "turns": 1,
                "buffs": null
            }
        },
        "FOUL_PLAY": {
            "id": "FOUL_PLAY",
            "power": 70,
            "energy": -50,
            "durationMs": 2000,
            "type": {
                "type": "POKEMON_TYPE_DARK",
                "names": {
                    "English": "Dark",
                    "German": "Unlicht",
                    "French": "T\u00e9n\u00e8bres",
                    "Italian": "Buio",
                    "Japanese": "\u3042\u304f",
                    "Korean": "\uc545",
                    "Spanish": "Siniestro"
                }
            },
            "names": {
                "English": "Foul Play",
                "German": "Schmarotzer",
                "French": "Tricherie",
                "Italian": "Ripicca",
                "Japanese": "\u30a4\u30ab\u30b5\u30de",
                "Korean": "\uc18d\uc784\uc218",
                "Spanish": "Juego Sucio"
            },
            "combat": {
                "energy": -40,
                "power": 65,
                "turns": 1,
                "buffs": null
            }
        }
    },
    "eliteQuickMoves": {
        "TACKLE_FAST": {
            "id": "TACKLE_FAST",
            "power": 5,
            "energy": 5,
            "durationMs": 500,
            "type": {
                "type": "POKEMON_TYPE_NORMAL",
                "names": {
                    "English": "Normal",
                    "German": "Normal",
                    "French": "Normal",
                    "Italian": "Normale",
                    "Japanese": "\u30ce\u30fc\u30de\u30eb",
                    "Korean": "\ub178\ub9d0",
                    "Spanish": "Normal"
                }
            },
            "names": {
                "English": "Tackle",
                "German": "Tackle",
                "French": "Charge",
                "Italian": "Azione",
                "Japanese": "\u305f\u3044\u3042\u305f\u308a",
                "Korean": "\ubab8\ud1b5\ubc15\uce58\uae30",
                "Spanish": "Placaje"
            },
            "combat": {
                "energy": 3,
                "power": 3,
                "turns": 1,
                "buffs": null
            }
        }
    },
    "eliteCinematicMoves": [],
    "assets": {
        "image": "https://raw.githubusercontent.com/RetroJohn86/PoGo-Unpacked-DL-Assets/main/Sprite/pm%20and%20portraits/pm101.icon.png",
        "shinyImage": "https://raw.githubusercontent.com/RetroJohn86/PoGo-Unpacked-DL-Assets/main/Sprite/pm%20and%20portraits/pm101.s.icon.png"
    },
    "regionForms": {
        "ELECTRODE_HISUIAN": {
            "id": "ELECTRODE",
            "formId": "ELECTRODE_HISUIAN",
            "dexNr": 101,
            "generation": 1,
            "names": {
                "English": "Hisuian Electrode",
                "German": "Hisuian-Lektrobal",
                "French": "\u00c9lectrode de Hisuian",
                "Italian": "Electrode di Hisuian",
                "Japanese": "\u30de\u30eb\u30de\u30a4\u30f3",
                "Korean": "\ubd90\ubcfc",
                "Spanish": "Electrode de Galar"
            },
            "stats": {
                "stamina": 155,
                "attack": 176,
                "defense": 176
            },
            "primaryType": {
                "type": "POKEMON_TYPE_ELECTRIC",
                "names": {
                    "English": "Electric",
                    "German": "Elektro",
                    "French": "\u00c9lectrik",
                    "Italian": "Elettro",
                    "Japanese": "\u3067\u3093\u304d",
                    "Korean": "\uc804\uae30",
                    "Spanish": "El\u00e9ctrico"
                }
            },
            "secondaryType": {
                "type": "POKEMON_TYPE_GRASS",
                "names": {
                    "English": "Grass",
                    "German": "Pflanze",
                    "French": "Plante",
                    "Italian": "Erba",
                    "Japanese": "\u304f\u3055",
                    "Korean": "\ud480",
                    "Spanish": "Planta"
                }
            },
            "pokemonClass": null,
            "quickMoves": {
                "THUNDER_SHOCK_FAST": {
                    "id": "THUNDER_SHOCK_FAST",
                    "power": 4,
                    "energy": 7,
                    "durationMs": 500,
                    "type": {
                        "type": "POKEMON_TYPE_ELECTRIC",
                        "names": {
                            "English": "Electric",
                            "German": "Elektro",
                            "French": "\u00c9lectrik",
                            "Italian": "Elettro",
                            "Japanese": "\u3067\u3093\u304d",
                            "Korean": "\uc804\uae30",
                            "Spanish": "El\u00e9ctrico"
                        }
                    },
                    "names": {
                        "English": "Thunder Shock",
                        "German": "Donnerschock",
                        "French": "\u00c9clair",
                        "Italian": "Tuonoshock",
                        "Japanese": "\u3067\u3093\u304d\u30b7\u30e7\u30c3\u30af",
                        "Korean": "\uc804\uae30\uc1fc\ud06c",
                        "Spanish": "Impactrueno"
                    },
                    "combat": {
                        "energy": 9,
                        "power": 4,
                        "turns": 2,
                        "buffs": null
                    }
                },
                "TACKLE_FAST": {
                    "id": "TACKLE_FAST",
                    "power": 5,
                    "energy": 5,
                    "durationMs": 500,
                    "type": {
                        "type": "POKEMON_TYPE_NORMAL",
                        "names": {
                            "English": "Normal",
                            "German": "Normal",
                            "French": "Normal",
                            "Italian": "Normale",
                            "Japanese": "\u30ce\u30fc\u30de\u30eb",
                            "Korean": "\ub178\ub9d0",
                            "Spanish": "Normal"
                        }
                    },
                    "names": {
                        "English": "Tackle",
                        "German": "Tackle",
                        "French": "Charge",
                        "Italian": "Azione",
                        "Japanese": "\u305f\u3044\u3042\u305f\u308a",
                        "Korean": "\ubab8\ud1b5\ubc15\uce58\uae30",
                        "Spanish": "Placaje"
                    },
                    "combat": {
                        "energy": 3,
                        "power": 3,
                        "turns": 1,
                        "buffs": null
                    }
                }
            },
            "cinematicMoves": {
                "SWIFT": {
                    "id": "SWIFT",
                    "power": 65,
                    "energy": -50,
                    "durationMs": 3000,
                    "type": {
                        "type": "POKEMON_TYPE_NORMAL",
                        "names": {
                            "English": "Normal",
                            "German": "Normal",
                            "French": "Normal",
                            "Italian": "Normale",
                            "Japanese": "\u30ce\u30fc\u30de\u30eb",
                            "Korean": "\ub178\ub9d0",
                            "Spanish": "Normal"
                        }
                    },
                    "names": {
                        "English": "Swift",
                        "German": "Sternschauer",
                        "French": "M\u00e9t\u00e9ores",
                        "Italian": "Comete",
                        "Japanese": "\u30b9\u30d4\u30fc\u30c9\u30b9\u30bf\u30fc",
                        "Korean": "\uc2a4\ud53c\ub4dc\uc2a4\ud0c0",
                        "Spanish": "Rapidez"
                    },
                    "combat": {
                        "energy": -35,
                        "power": 55,
                        "turns": 1,
                        "buffs": null
                    }
                },
                "WILD_CHARGE": {
                    "id": "WILD_CHARGE",
                    "power": 90,
                    "energy": -50,
                    "durationMs": 2500,
                    "type": {
                        "type": "POKEMON_TYPE_ELECTRIC",
                        "names": {
                            "English": "Electric",
                            "German": "Elektro",
                            "French": "\u00c9lectrik",
                            "Italian": "Elettro",
                            "Japanese": "\u3067\u3093\u304d",
                            "Korean": "\uc804\uae30",
                            "Spanish": "El\u00e9ctrico"
                        }
                    },
                    "names": {
                        "English": "Wild Charge",
                        "German": "Stromsto\u00df",
                        "French": "\u00c9clair Fou",
                        "Italian": "Sprizzalampo",
                        "Japanese": "\u30ef\u30a4\u30eb\u30c9\u30dc\u30eb\u30c8",
                        "Korean": "\uc640\uc77c\ub4dc\ubcfc\ud2b8",
                        "Spanish": "Voltio Cruel"
                    },
                    "combat": {
                        "energy": -45,
                        "power": 100,
                        "turns": 1,
                        "buffs": {
                            "activationChance": 100,
                            "attackerAttackStatsChange": null,
                            "attackerDefenseStatsChange": -2,
                            "targetAttackStatsChange": null,
                            "targetDefenseStatsChange": null
                        }
                    }
                },
                "ENERGY_BALL": {
                    "id": "ENERGY_BALL",
                    "power": 90,
                    "energy": -50,
                    "durationMs": 4000,
                    "type": {
                        "type": "POKEMON_TYPE_GRASS",
                        "names": {
                            "English": "Grass",
                            "German": "Pflanze",
                            "French": "Plante",
                            "Italian": "Erba",
                            "Japanese": "\u304f\u3055",
                            "Korean": "\ud480",
                            "Spanish": "Planta"
                        }
                    },
                    "names": {
                        "English": "Energy Ball",
                        "German": "Energieball",
                        "French": "\u00c9co-Sph\u00e8re",
                        "Italian": "Energipalla",
                        "Japanese": "\u30a8\u30ca\u30b8\u30fc\u30dc\u30fc\u30eb",
                        "Korean": "\uc5d0\ub108\uc9c0\ubcfc",
                        "Spanish": "Energibola"
                    },
                    "combat": {
                        "energy": -55,
                        "power": 90,
                        "turns": 1,
                        "buffs": {
                            "activationChance": 10,
                            "attackerAttackStatsChange": null,
                            "attackerDefenseStatsChange": null,
                            "targetAttackStatsChange": null,
                            "targetDefenseStatsChange": -1
                        }
                    }
                }
            },
            "eliteQuickMoves": [],
            "eliteCinematicMoves": [],
            "assets": {
                "image": "https://raw.githubusercontent.com/RetroJohn86/PoGo-Unpacked-DL-Assets/main/Sprite/pm%20and%20portraits/pm101.fHISUIAN.icon.png",
                "shinyImage": "https://raw.githubusercontent.com/RetroJohn86/PoGo-Unpacked-DL-Assets/main/Sprite/pm%20and%20portraits/pm101.fHISUIAN.s.icon.png"
            },
            "regionForms": [],
            "evolutions": [],
            "hasMegaEvolution": false,
            "megaEvolutions": [],
            "hasGigantamaxEvolution": false
        }
    },
    "evolutions": [],
    "hasMegaEvolution": false,
    "megaEvolutions": [],
    "hasGigantamaxEvolution": false,
    "assetForms": [
        {
            "form": "HISUIAN",
            "costume": null,
            "isFemale": false,
            "image": "https://raw.githubusercontent.com/RetroJohn86/PoGo-Unpacked-DL-Assets/main/Sprite/pm%20and%20portraits/pm101.fHISUIAN.icon.png",
            "shinyImage": "https://raw.githubusercontent.com/RetroJohn86/PoGo-Unpacked-DL-Assets/main/Sprite/pm%20and%20portraits/pm101.fHISUIAN.s.icon.png"
        },
        {
            "form": null,
            "costume": null,
            "isFemale": false,
            "image": "https://raw.githubusercontent.com/RetroJohn86/PoGo-Unpacked-DL-Assets/main/Sprite/pm%20and%20portraits/pm101.icon.png",
            "shinyImage": "https://raw.githubusercontent.com/RetroJohn86/PoGo-Unpacked-DL-Assets/main/Sprite/pm%20and%20portraits/pm101.s.icon.png"
        }
    ]
}