{
    "id": "PORYGON2",
    "formId": "PORYGON2",
    "dexNr": 233,
    "generation": 2,
    "names": {
        "English": "Porygon2",
        "German": "Porygon2",
        "French": "Porygon2",
        "Italian": "Porygon2",
        "Japanese": "\u30dd\u30ea\u30b4\u30f3\uff12",
        "Korean": "\ud3f4\ub9ac\uace42",
        "Spanish": "Porygon2"
    },
    "stats": {
        "stamina": 198,
        "attack": 198,
        "defense": 180
    },
    "primaryType": {
        "type": "POKEMON_TYPE_NORMAL",
        "names": {
            "English": "Normal",
            "German": "Normal",
            "French": "Normal",
            "Italian": "Normale",
            "Japanese": "\u30ce\u30fc\u30de\u30eb",
            "Korean": "\ub178\ub9d0",
            "Spanish": "Normal"
        }
    },
    "secondaryType": null,
    "pokemonClass": null,
    "quickMoves": {
        "HIDDEN_POWER_FAST": {
            "id": "HIDDEN_POWER_FAST",
            "power": 15,
            "energy": 15,
            "durationMs": 1500,
            "type": {
                "type": "POKEMON_TYPE_NORMAL",
                "names": {
                    "English": "Normal",
                    "German": "Normal",
                    "French": "Normal",
                    "Italian": "Normale",
                    "Japanese": "\u30ce\u30fc\u30de\u30eb",
                    "Korean": "\ub178\ub9d0",
                    "Spanish": "Normal"
                }
            },
            "names": {
                "English": "Hidden Power",
                "German": "Kraftreserve",
                "French": "Puissance Cach\u00e9e",
                "Italian": "Introforza",
                "Japanese": "\u3081\u3056\u3081\u308b\u30d1\u30ef\u30fc",
                "Korean": "\uc7a0\uc7ac\ud30c\uc6cc",
                "Spanish": "Poder Oculto"
            },
            "combat": {
                "energy": 8,
                "power": 9,
                "turns": 3,
                "buffs": null
            }
        },
        "CHARGE_BEAM_FAST": {
            "id": "CHARGE_BEAM_FAST",
            "power": 7,
            "energy": 14,
            "durationMs": 1000,
            "type": {
                "type": "POKEMON_TYPE_ELECTRIC",
                "names": {
                    "English": "Electric",
                    "German": "Elektro",
                    "French": "\u00c9lectrik",
                    "Italian": "Elettro",
                    "Japanese": "\u3067\u3093\u304d",
                    "Korean": "\uc804\uae30",
                    "Spanish": "El\u00e9ctrico"
                }
            },
            "names": {
                "English": "Charge Beam",
                "German": "Ladestrahl",
                "French": "Rayon Charg\u00e9",
                "Italian": "Raggioscossa",
                "Japanese": "\u30c1\u30e3\u30fc\u30b8\u30d3\u30fc\u30e0",
                "Korean": "\ucc28\uc9c0\ube54",
                "Spanish": "Rayo Carga"
            },
            "combat": {
                "energy": 11,
                "power": 5,
                "turns": 3,
                "buffs": null
            }
        },
        "LOCK_ON_FAST": {
            "id": "LOCK_ON_FAST",
            "power": 2,
            "energy": 10,
            "durationMs": 500,
            "type": {
                "type": "POKEMON_TYPE_NORMAL",
                "names": {
                    "English": "Normal",
                    "German": "Normal",
                    "French": "Normal",
                    "Italian": "Normale",
                    "Japanese": "\u30ce\u30fc\u30de\u30eb",
                    "Korean": "\ub178\ub9d0",
                    "Spanish": "Normal"
                }
            },
            "names": {
                "English": "Lock-On",
                "German": "Zielschuss",
                "French": "Verrouillage",
                "Italian": "Localizza",
                "Japanese": "\u30ed\u30c3\u30af\u30aa\u30f3",
                "Korean": "\ub85d\uc628",
                "Spanish": "Fijar Blanco"
            },
            "combat": {
                "energy": 5,
                "power": 1,
                "turns": 1,
                "buffs": null
            }
        }
    },
    "cinematicMoves": {
        "SOLAR_BEAM": {
            "id": "SOLAR_BEAM",
            "power": 180,
            "energy": -100,
            "durationMs": 5000,
            "type": {
                "type": "POKEMON_TYPE_GRASS",
                "names": {
                    "English": "Grass",
                    "German": "Pflanze",
                    "French": "Plante",
                    "Italian": "Erba",
                    "Japanese": "\u304f\u3055",
                    "Korean": "\ud480",
                    "Spanish": "Planta"
                }
            },
            "names": {
                "English": "Solar Beam",
                "German": "Solarstrahl",
                "French": "Lance-Soleil",
                "Italian": "Solarraggio",
                "Japanese": "\u30bd\u30fc\u30e9\u30fc\u30d3\u30fc\u30e0",
                "Korean": "\uc194\ub77c\ube54",
                "Spanish": "Rayo Solar"
            },
            "combat": {
                "energy": -80,
                "power": 150,
                "turns": 1,
                "buffs": null
            }
        },
        "HYPER_BEAM": {
            "id": "HYPER_BEAM",
            "power": 150,
            "energy": -100,
            "durationMs": 4000,
            "type": {
                "type": "POKEMON_TYPE_NORMAL",
                "names": {
                    "English": "Normal",
                    "German": "Normal",
                    "French": "Normal",
                    "Italian": "Normale",
                    "Japanese": "\u30ce\u30fc\u30de\u30eb",
                    "Korean": "\ub178\ub9d0",
                    "Spanish": "Normal"
                }
            },
            "names": {
                "English": "Hyper Beam",
                "German": "Hyperstrahl",
                "French": "Ultralaser",
                "Italian": "Iper Raggio",
                "Japanese": "\u306f\u304b\u3044\u3053\u3046\u305b\u3093",
                "Korean": "\ud30c\uad34\uad11\uc120",
                "Spanish": "Hiperrayo"
            },
            "combat": {
                "energy": -80,
                "power": 150,
                "turns": 1,
                "buffs": null
            }
        },
        "ZAP_CANNON": {
            "id": "ZAP_CANNON",
            "power": 140,
            "energy": -100,
            "durationMs": 3500,
            "type": {
                "type": "POKEMON_TYPE_ELECTRIC",
                "names": {
                    "English": "Electric",
                    "German": "Elektro",
                    "French": "\u00c9lectrik",
                    "Italian": "Elettro",
                    "Japanese": "\u3067\u3093\u304d",
                    "Korean": "\uc804\uae30",
                    "Spanish": "El\u00e9ctrico"
                }
            },
            "names": {
                "English": "Zap Cannon",
                "German": "Blitzkanone",
                "French": "\u00c9lecanon",
                "Italian": "Falcecannone",
                "Japanese": "\u3067\u3093\u3058\u307b\u3046",
                "Korean": "\uc804\uc790\ud3ec",
                "Spanish": "Electroca\u00f1\u00f3n"
            },
            "combat": {
                "energy": -80,
                "power": 150,
                "turns": 1,
                "buffs": {
                    "activationChance": 33,
                    "attackerAttackStatsChange": null,
                    "attackerDefenseStatsChange": null,
                    "targetAttackStatsChange": -1,
                    "targetDefenseStatsChange": null
                }
            }
        },
        "TRI_ATTACK": {
            "id": "TRI_ATTACK",
            "power": 75,
            "energy": -50,
            "durationMs": 2500,
            "type": {
                "type": "POKEMON_TYPE_NORMAL",
                "names": {
                    "English": "Normal",
                    "German": "Normal",
                    "French": "Normal",
                    "Italian": "Normale",
                    "Japanese": "\u30ce\u30fc\u30de\u30eb",
                    "Korean": "\ub178\ub9d0",
                    "Spanish": "Normal"
                }
            },
            "names": {
                "English": "Tri Attack",
                "German": "Triplette",
                "French": "Triplattaque",
                "Italian": "Tripletta",
                "Japanese": "\u30c8\u30e9\u30a4\u30a2\u30bf\u30c3\u30af",
                "Korean": "\ud2b8\ub77c\uc774\uc5b4\ud0dd",
                "Spanish": "Triataque"
            },
            "combat": {
                "energy": -50,
                "power": 65,
                "turns": 1,
                "buffs": {
                    "activationChance": 50,
                    "attackerAttackStatsChange": null,
                    "attackerDefenseStatsChange": null,
                    "targetAttackStatsChange": -1,
                    "targetDefenseStatsChange": -1
                }
            }
        }
    },
    "eliteQuickMoves": [],
    "eliteCinematicMoves": [],
    "assets": {
        "image": "https://raw.githubusercontent.com/RetroJohn86/PoGo-Unpacked-DL-Assets/main/Sprite/pm%20and%20portraits/pm233.icon.png",
        "shinyImage": "https://raw.githubusercontent.com/RetroJohn86/PoGo-Unpacked-DL-Assets/main/Sprite/pm%20and%20portraits/pm233.s.icon.png"
    },
    "regionForms": [],
    "evolutions": [
        {
            "id": "PORYGON_Z",
            "formId": "PORYGON_Z_NORMAL",
            "candies": 100,
            "item": {
                "id": "ITEM_GEN4_EVOLUTION_STONE",
                "names": {
                    "English": "Sinnoh Stone",
                    "German": "Sinnoh-Stein",
                    "French": "Pierre Sinnoh",
                    "Italian": "Pietra Sinnoh",
                    "Japanese": "\u30b7\u30f3\u30aa\u30a6\u306e\u3044\u3057",
                    "Korean": "\uc2e0\uc624\uc758 \ub3cc",
                    "Spanish": "Piedra Sinnoh"
                }
            },
            "quests": []
        }
    ],
    "hasMegaEvolution": false,
    "megaEvolutions": [],
    "hasGigantamaxEvolution": false,
    "assetForms": [
        {
            "form": null,
            "costume": null,
            "isFemale": false,
            "image": "https://raw.githubusercontent.com/RetroJohn86/PoGo-Unpacked-DL-Assets/main/Sprite/pm%20and%20portraits/pm233.icon.png",
            "shinyImage": "https://raw.githubusercontent.com/RetroJohn86/PoGo-Unpacked-DL-Assets/main/Sprite/pm%20and%20portraits/pm233.s.icon.png"
        }
    ]
}