{
    "id": "SCRAFTY",
    "formId": "SCRAFTY",
    "dexNr": 560,
    "generation": 5,
    "names": {
        "English": "Scrafty",
        "German": "Irokex",
        "French": "Bagga\u00efd",
        "Italian": "Scrafty",
        "Japanese": "\u30ba\u30eb\u30ba\u30ad\u30f3",
        "Korean": "\uace4\uc728\uac70\ub2c8",
        "Spanish": "Scrafty"
    },
    "stats": {
        "stamina": 163,
        "attack": 163,
        "defense": 222
    },
    "primaryType": {
        "type": "POKEMON_TYPE_DARK",
        "names": {
            "English": "Dark",
            "German": "Unlicht",
            "French": "T\u00e9n\u00e8bres",
            "Italian": "Buio",
            "Japanese": "\u3042\u304f",
            "Korean": "\uc545",
            "Spanish": "Siniestro"
        }
    },
    "secondaryType": {
        "type": "POKEMON_TYPE_FIGHTING",
        "names": {
            "English": "Fighting",
            "German": "Kampf",
            "French": "Combat",
            "Italian": "Lotta",
            "Japanese": "\u304b\u304f\u3068\u3046",
            "Korean": "\uaca9\ud22c",
            "Spanish": "Lucha"
        }
    },
    "pokemonClass": null,
    "quickMoves": {
        "COUNTER_FAST": {
            "id": "COUNTER_FAST",
            "power": 13,
            "energy": 9,
            "durationMs": 1000,
            "type": {
                "type": "POKEMON_TYPE_FIGHTING",
                "names": {
                    "English": "Fighting",
                    "German": "Kampf",
                    "French": "Combat",
                    "Italian": "Lotta",
                    "Japanese": "\u304b\u304f\u3068\u3046",
                    "Korean": "\uaca9\ud22c",
                    "Spanish": "Lucha"
                }
            },
            "names": {
                "English": "Counter",
                "German": "Konter",
                "French": "Riposte",
                "Italian": "Contrattacco",
                "Japanese": "\u30ab\u30a6\u30f3\u30bf\u30fc",
                "Korean": "\uce74\uc6b4\ud130",
                "Spanish": "Contraataque"
            },
            "combat": {
                "energy": 6,
                "power": 8,
                "turns": 2,
                "buffs": null
            }
        },
        "SNARL_FAST": {
            "id": "SNARL_FAST",
            "power": 11,
            "energy": 13,
            "durationMs": 1000,
            "type": {
                "type": "POKEMON_TYPE_DARK",
                "names": {
                    "English": "Dark",
                    "German": "Unlicht",
                    "French": "T\u00e9n\u00e8bres",
                    "Italian": "Buio",
                    "Japanese": "\u3042\u304f",
                    "Korean": "\uc545",
                    "Spanish": "Siniestro"
                }
            },
            "names": {
                "English": "Snarl",
                "German": "Standpauke",
                "French": "Aboiement",
                "Italian": "Urlorabbia",
                "Japanese": "\u30d0\u30fc\u30af\u30a2\u30a6\u30c8",
                "Korean": "\ubc14\ud06c\uc544\uc6c3",
                "Spanish": "Alarido"
            },
            "combat": {
                "energy": 13,
                "power": 5,
                "turns": 3,
                "buffs": null
            }
        }
    },
    "cinematicMoves": {
        "ACID_SPRAY": {
            "id": "ACID_SPRAY",
            "power": 20,
            "energy": -50,
            "durationMs": 3000,
            "type": {
                "type": "POKEMON_TYPE_POISON",
                "names": {
                    "English": "Poison",
                    "German": "Gift",
                    "French": "Poison",
                    "Italian": "Veleno",
                    "Japanese": "\u3069\u304f",
                    "Korean": "\ub3c5",
                    "Spanish": "Veneno"
                }
            },
            "names": {
                "English": "Acid Spray",
                "German": "S\u00e4urespeier",
                "French": "Bombe Acide",
                "Italian": "Acidobomba",
                "Japanese": "\u30a2\u30b7\u30c3\u30c9\u30dc\u30e0",
                "Korean": "\uc560\uc2dc\ub4dc\ubd04",
                "Spanish": "Bomba \u00c1cida"
            },
            "combat": {
                "energy": -45,
                "power": 20,
                "turns": 1,
                "buffs": {
                    "activationChance": 100,
                    "attackerAttackStatsChange": null,
                    "attackerDefenseStatsChange": null,
                    "targetAttackStatsChange": null,
                    "targetDefenseStatsChange": -2
                }
            }
        },
        "POWER_UP_PUNCH": {
            "id": "POWER_UP_PUNCH",
            "power": 50,
            "energy": -33,
            "durationMs": 2000,
            "type": {
                "type": "POKEMON_TYPE_FIGHTING",
                "names": {
                    "English": "Fighting",
                    "German": "Kampf",
                    "French": "Combat",
                    "Italian": "Lotta",
                    "Japanese": "\u304b\u304f\u3068\u3046",
                    "Korean": "\uaca9\ud22c",
                    "Spanish": "Lucha"
                }
            },
            "names": {
                "English": "Power-Up Punch",
                "German": "Steigerungshieb",
                "French": "Poing Boost",
                "Italian": "Crescipugno",
                "Japanese": "\u30b0\u30ed\u30a6\u30d1\u30f3\u30c1",
                "Korean": "\uadf8\ub85c\uc6b0\ud380\uce58",
                "Spanish": "Pu\u00f1o Incremento"
            },
            "combat": {
                "energy": -35,
                "power": 20,
                "turns": 1,
                "buffs": {
                    "activationChance": 100,
                    "attackerAttackStatsChange": 1,
                    "attackerDefenseStatsChange": null,
                    "targetAttackStatsChange": null,
                    "targetDefenseStatsChange": null
                }
            }
        },
        "FOUL_PLAY": {
            "id": "FOUL_PLAY",
            "power": 70,
            "energy": -50,
            "durationMs": 2000,
            "type": {
                "type": "POKEMON_TYPE_DARK",
                "names": {
                    "English": "Dark",
                    "German": "Unlicht",
                    "French": "T\u00e9n\u00e8bres",
                    "Italian": "Buio",
                    "Japanese": "\u3042\u304f",
                    "Korean": "\uc545",
                    "Spanish": "Siniestro"
                }
            },
            "names": {
                "English": "Foul Play",
                "German": "Schmarotzer",
                "French": "Tricherie",
                "Italian": "Ripicca",
                "Japanese": "\u30a4\u30ab\u30b5\u30de",
                "Korean": "\uc18d\uc784\uc218",
                "Spanish": "Juego Sucio"
            },
            "combat": {
                "energy": -40,
                "power": 65,
                "turns": 1,
                "buffs": null
            }
        },
        "THUNDER_PUNCH": {
            "id": "THUNDER_PUNCH",
            "power": 50,
            "energy": -33,
            "durationMs": 2000,
            "type": {
                "type": "POKEMON_TYPE_ELECTRIC",
                "names": {
                    "English": "Electric",
                    "German": "Elektro",
                    "French": "\u00c9lectrik",
                    "Italian": "Elettro",
                    "Japanese": "\u3067\u3093\u304d",
                    "Korean": "\uc804\uae30",
                    "Spanish": "El\u00e9ctrico"
                }
            },
            "names": {
                "English": "Thunder Punch",
                "German": "Donnerschlag",
                "French": "Poing \u00c9clair",
                "Italian": "Tuonopugno",
                "Japanese": "\u304b\u307f\u306a\u308a\u30d1\u30f3\u30c1",
                "Korean": "\ubc88\uac1c\ud380\uce58",
                "Spanish": "Pu\u00f1o Trueno"
            },
            "combat": {
                "energy": -40,
                "power": 60,
                "turns": 1,
                "buffs": null
            }
        },
        "UPPER_HAND": {
            "id": "UPPER_HAND",
            "power": 50,
            "energy": -33,
            "durationMs": 2000,
            "type": {
                "type": "POKEMON_TYPE_FIGHTING",
                "names": {
                    "English": "Fighting",
                    "German": "Kampf",
                    "French": "Combat",
                    "Italian": "Lotta",
                    "Japanese": "\u304b\u304f\u3068\u3046",
                    "Korean": "\uaca9\ud22c",
                    "Spanish": "Lucha"
                }
            },
            "names": {
                "English": "Upper Hand",
                "German": "Schnellkonter",
                "French": "Prio-Parade",
                "Italian": "Colpo di Mano",
                "Japanese": "\u306f\u3084\u3066\u304c\u3048\u3057",
                "Korean": "\uae30\uc120\uc81c\uc555",
                "Spanish": "Palma Rauda"
            },
            "combat": {
                "energy": -40,
                "power": 70,
                "turns": 1,
                "buffs": {
                    "activationChance": 30,
                    "attackerAttackStatsChange": null,
                    "attackerDefenseStatsChange": null,
                    "targetAttackStatsChange": null,
                    "targetDefenseStatsChange": -1
                }
            }
        }
    },
    "eliteQuickMoves": [],
    "eliteCinematicMoves": [],
    "assets": {
        "image": "https://raw.githubusercontent.com/RetroJohn86/PoGo-Unpacked-DL-Assets/main/Sprite/pm%20and%20portraits/pm560.icon.png",
        "shinyImage": "https://raw.githubusercontent.com/RetroJohn86/PoGo-Unpacked-DL-Assets/main/Sprite/pm%20and%20portraits/pm560.s.icon.png"
    },
    "regionForms": [],
    "evolutions": [],
    "hasMegaEvolution": false,
    "megaEvolutions": [],
    "hasGigantamaxEvolution": false,
    "assetForms": [
        {
            "form": null,
            "costume": null,
            "isFemale": false,
            "image": "https://raw.githubusercontent.com/RetroJohn86/PoGo-Unpacked-DL-Assets/main/Sprite/pm%20and%20portraits/pm560.icon.png",
            "shinyImage": "https://raw.githubusercontent.com/RetroJohn86/PoGo-Unpacked-DL-Assets/main/Sprite/pm%20and%20portraits/pm560.s.icon.png"
        }
    ]
}