{
    "id": "JUMPLUFF",
    "formId": "JUMPLUFF",
    "dexNr": 189,
    "generation": 2,
    "names": {
        "English": "Jumpluff",
        "German": "Papungha",
        "French": "Cotovol",
        "Italian": "Jumpluff",
        "Japanese": "\u30ef\u30bf\u30c3\u30b3",
        "Korean": "\uc19c\uc19c\ucf54",
        "Spanish": "Jumpluff"
    },
    "stats": {
        "stamina": 181,
        "attack": 118,
        "defense": 183
    },
    "primaryType": {
        "type": "POKEMON_TYPE_GRASS",
        "names": {
            "English": "Grass",
            "German": "Pflanze",
            "French": "Plante",
            "Italian": "Erba",
            "Japanese": "\u304f\u3055",
            "Korean": "\ud480",
            "Spanish": "Planta"
        }
    },
    "secondaryType": {
        "type": "POKEMON_TYPE_FLYING",
        "names": {
            "English": "Flying",
            "German": "Flug",
            "French": "Vol",
            "Italian": "Volante",
            "Japanese": "\u3072\u3053\u3046",
            "Korean": "\ube44\ud589",
            "Spanish": "Volador"
        }
    },
    "pokemonClass": null,
    "quickMoves": {
        "INFESTATION_FAST": {
            "id": "INFESTATION_FAST",
            "power": 9,
            "energy": 13,
            "durationMs": 1000,
            "type": {
                "type": "POKEMON_TYPE_BUG",
                "names": {
                    "English": "Bug",
                    "German": "K\u00e4fer",
                    "French": "Insecte",
                    "Italian": "Coleottero",
                    "Japanese": "\u3080\u3057",
                    "Korean": "\ubc8c\ub808",
                    "Spanish": "Bicho"
                }
            },
            "names": {
                "English": "Infestation",
                "German": "Plage",
                "French": "Harc\u00e8lement",
                "Italian": "Assillo",
                "Japanese": "\u307e\u3068\u308f\u308a\u3064\u304f",
                "Korean": "\uc5c9\uaca8\ubd99\uae30",
                "Spanish": "Acoso"
            },
            "combat": {
                "energy": 12,
                "power": 6,
                "turns": 3,
                "buffs": null
            }
        },
        "BULLET_SEED_FAST": {
            "id": "BULLET_SEED_FAST",
            "power": 7,
            "energy": 13,
            "durationMs": 1000,
            "type": {
                "type": "POKEMON_TYPE_GRASS",
                "names": {
                    "English": "Grass",
                    "German": "Pflanze",
                    "French": "Plante",
                    "Italian": "Erba",
                    "Japanese": "\u304f\u3055",
                    "Korean": "\ud480",
                    "Spanish": "Planta"
                }
            },
            "names": {
                "English": "Bullet Seed",
                "German": "Kugelsaat",
                "French": "Balle Graine",
                "Italian": "Semitraglia",
                "Japanese": "\u30bf\u30cd\u30de\u30b7\u30f3\u30ac\u30f3",
                "Korean": "\uc528\uae30\uad00\ucd1d",
                "Spanish": "Semilladora"
            },
            "combat": {
                "energy": 13,
                "power": 5,
                "turns": 3,
                "buffs": null
            }
        },
        "FAIRY_WIND_FAST": {
            "id": "FAIRY_WIND_FAST",
            "power": 9,
            "energy": 13,
            "durationMs": 1000,
            "type": {
                "type": "POKEMON_TYPE_FAIRY",
                "names": {
                    "English": "Fairy",
                    "German": "Fee",
                    "French": "F\u00e9e",
                    "Italian": "Folletto",
                    "Japanese": "\u30d5\u30a7\u30a2\u30ea\u30fc",
                    "Korean": "\ud398\uc5b4\ub9ac",
                    "Spanish": "Hada"
                }
            },
            "names": {
                "English": "Fairy Wind",
                "German": "Feenbrise",
                "French": "Vent F\u00e9\u00e9rique",
                "Italian": "Vento di Fata",
                "Japanese": "\u3088\u3046\u305b\u3044\u306e\u304b\u305c",
                "Korean": "\uc694\uc815\uc758\ubc14\ub78c",
                "Spanish": "Viento Fe\u00e9rico"
            },
            "combat": {
                "energy": 9,
                "power": 4,
                "turns": 2,
                "buffs": null
            }
        }
    },
    "cinematicMoves": {
        "ENERGY_BALL": {
            "id": "ENERGY_BALL",
            "power": 90,
            "energy": -50,
            "durationMs": 4000,
            "type": {
                "type": "POKEMON_TYPE_GRASS",
                "names": {
                    "English": "Grass",
                    "German": "Pflanze",
                    "French": "Plante",
                    "Italian": "Erba",
                    "Japanese": "\u304f\u3055",
                    "Korean": "\ud480",
                    "Spanish": "Planta"
                }
            },
            "names": {
                "English": "Energy Ball",
                "German": "Energieball",
                "French": "\u00c9co-Sph\u00e8re",
                "Italian": "Energipalla",
                "Japanese": "\u30a8\u30ca\u30b8\u30fc\u30dc\u30fc\u30eb",
                "Korean": "\uc5d0\ub108\uc9c0\ubcfc",
                "Spanish": "Energibola"
            },
            "combat": {
                "energy": -55,
                "power": 90,
                "turns": 1,
                "buffs": {
                    "activationChance": 10,
                    "attackerAttackStatsChange": null,
                    "attackerDefenseStatsChange": null,
                    "targetAttackStatsChange": null,
                    "targetDefenseStatsChange": -1
                }
            }
        },
        "DAZZLING_GLEAM": {
            "id": "DAZZLING_GLEAM",
            "power": 100,
            "energy": -50,
            "durationMs": 3500,
            "type": {
                "type": "POKEMON_TYPE_FAIRY",
                "names": {
                    "English": "Fairy",
                    "German": "Fee",
                    "French": "F\u00e9e",
                    "Italian": "Folletto",
                    "Japanese": "\u30d5\u30a7\u30a2\u30ea\u30fc",
                    "Korean": "\ud398\uc5b4\ub9ac",
                    "Spanish": "Hada"
                }
            },
            "names": {
                "English": "Dazzling Gleam",
                "German": "Zauberschein",
                "French": "\u00c9clat Magique",
                "Italian": "Magibrillio",
                "Japanese": "\u30de\u30b8\u30ab\u30eb\u30b7\u30e3\u30a4\u30f3",
                "Korean": "\ub9e4\uc9c0\uceec\uc0e4\uc778",
                "Spanish": "Brillo M\u00e1gico"
            },
            "combat": {
                "energy": -55,
                "power": 90,
                "turns": 1,
                "buffs": null
            }
        },
        "SOLAR_BEAM": {
            "id": "SOLAR_BEAM",
            "power": 180,
            "energy": -100,
            "durationMs": 5000,
            "type": {
                "type": "POKEMON_TYPE_GRASS",
                "names": {
                    "English": "Grass",
                    "German": "Pflanze",
                    "French": "Plante",
                    "Italian": "Erba",
                    "Japanese": "\u304f\u3055",
                    "Korean": "\ud480",
                    "Spanish": "Planta"
                }
            },
            "names": {
                "English": "Solar Beam",
                "German": "Solarstrahl",
                "French": "Lance-Soleil",
                "Italian": "Solarraggio",
                "Japanese": "\u30bd\u30fc\u30e9\u30fc\u30d3\u30fc\u30e0",
                "Korean": "\uc194\ub77c\ube54",
                "Spanish": "Rayo Solar"
            },
            "combat": {
                "energy": -80,
                "power": 150,
                "turns": 1,
                "buffs": null
            }
        },
        "AERIAL_ACE": {
            "id": "AERIAL_ACE",
            "power": 55,
            "energy": -33,
            "durationMs": 2500,
            "type": {
                "type": "POKEMON_TYPE_FLYING",
                "names": {
                    "English": "Flying",
                    "German": "Flug",
                    "French": "Vol",
                    "Italian": "Volante",
                    "Japanese": "\u3072\u3053\u3046",
                    "Korean": "\ube44\ud589",
                    "Spanish": "Volador"
                }
            },
            "names": {
                "English": "Aerial Ace",
                "German": "Aero-Ass",
                "French": "A\u00e9ropique",
                "Italian": "Aeroassalto",
                "Japanese": "\u3064\u3070\u3081\u304c\u3048\u3057",
                "Korean": "\uc81c\ube44\ubc18\ud658",
                "Spanish": "Golpe A\u00e9reo"
            },
            "combat": {
                "energy": -45,
                "power": 60,
                "turns": 1,
                "buffs": null
            }
        }
    },
    "eliteQuickMoves": [],
    "eliteCinematicMoves": {
        "ACROBATICS": {
            "id": "ACROBATICS",
            "power": 100,
            "energy": -100,
            "durationMs": 2000,
            "type": {
                "type": "POKEMON_TYPE_FLYING",
                "names": {
                    "English": "Flying",
                    "German": "Flug",
                    "French": "Vol",
                    "Italian": "Volante",
                    "Japanese": "\u3072\u3053\u3046",
                    "Korean": "\ube44\ud589",
                    "Spanish": "Volador"
                }
            },
            "names": {
                "English": "Acrobatics",
                "German": "Akrobatik",
                "French": "Acrobatie",
                "Italian": "Acrobazia",
                "Japanese": "\u30a2\u30af\u30ed\u30d0\u30c3\u30c8",
                "Korean": "\uc560\ud06c\ub7ec\ubc43",
                "Spanish": "Acr\u00f3bata"
            },
            "combat": {
                "energy": -55,
                "power": 110,
                "turns": 1,
                "buffs": null
            }
        }
    },
    "assets": {
        "image": "https://raw.githubusercontent.com/RetroJohn86/PoGo-Unpacked-DL-Assets/main/Sprite/pm%20and%20portraits/pm189.icon.png",
        "shinyImage": "https://raw.githubusercontent.com/RetroJohn86/PoGo-Unpacked-DL-Assets/main/Sprite/pm%20and%20portraits/pm189.s.icon.png"
    },
    "regionForms": [],
    "evolutions": [],
    "hasMegaEvolution": false,
    "megaEvolutions": [],
    "hasGigantamaxEvolution": false,
    "assetForms": [
        {
            "form": null,
            "costume": null,
            "isFemale": false,
            "image": "https://raw.githubusercontent.com/RetroJohn86/PoGo-Unpacked-DL-Assets/main/Sprite/pm%20and%20portraits/pm189.icon.png",
            "shinyImage": "https://raw.githubusercontent.com/RetroJohn86/PoGo-Unpacked-DL-Assets/main/Sprite/pm%20and%20portraits/pm189.s.icon.png"
        }
    ]
}