{
    "id": "SCOVILLAIN",
    "formId": "SCOVILLAIN",
    "dexNr": 952,
    "generation": 9,
    "names": {
        "English": "Scovillain",
        "German": "Halupenjo",
        "French": "Scovilain",
        "Italian": "Scovillain",
        "Japanese": "\u30b9\u30b3\u30f4\u30a3\u30e9\u30f3",
        "Korean": "\uc2a4\ucf54\ube4c\ub7f0",
        "Spanish": "Scovillain"
    },
    "stats": {
        "stamina": 163,
        "attack": 216,
        "defense": 130
    },
    "primaryType": {
        "type": "POKEMON_TYPE_GRASS",
        "names": {
            "English": "Grass",
            "German": "Pflanze",
            "French": "Plante",
            "Italian": "Erba",
            "Japanese": "\u304f\u3055",
            "Korean": "\ud480",
            "Spanish": "Planta"
        }
    },
    "secondaryType": {
        "type": "POKEMON_TYPE_FIRE",
        "names": {
            "English": "Fire",
            "German": "Feuer",
            "French": "Feu",
            "Italian": "Fuoco",
            "Japanese": "\u307b\u306e\u304a",
            "Korean": "\ubd88\uaf43",
            "Spanish": "Fuego"
        }
    },
    "pokemonClass": null,
    "quickMoves": {
        "LEAFAGE_FAST": {
            "id": "LEAFAGE_FAST",
            "power": 6,
            "energy": 4,
            "durationMs": 500,
            "type": {
                "type": "POKEMON_TYPE_GRASS",
                "names": {
                    "English": "Grass",
                    "German": "Pflanze",
                    "French": "Plante",
                    "Italian": "Erba",
                    "Japanese": "\u304f\u3055",
                    "Korean": "\ud480",
                    "Spanish": "Planta"
                }
            },
            "names": {
                "English": "Leafage",
                "German": "Blattwerk",
                "French": "Feuillage",
                "Italian": "Fogliame",
                "Japanese": "\u3053\u306e\u306f",
                "Korean": "\ub098\ubb47\uc78e",
                "Spanish": "Follaje"
            },
            "combat": {
                "energy": 8,
                "power": 6,
                "turns": 2,
                "buffs": null
            }
        },
        "FIRE_FANG_FAST": {
            "id": "FIRE_FANG_FAST",
            "power": 13,
            "energy": 9,
            "durationMs": 1000,
            "type": {
                "type": "POKEMON_TYPE_FIRE",
                "names": {
                    "English": "Fire",
                    "German": "Feuer",
                    "French": "Feu",
                    "Italian": "Fuoco",
                    "Japanese": "\u307b\u306e\u304a",
                    "Korean": "\ubd88\uaf43",
                    "Spanish": "Fuego"
                }
            },
            "names": {
                "English": "Fire Fang",
                "German": "Feuerzahn",
                "French": "Crocs Feu",
                "Italian": "Rogodenti",
                "Japanese": "\u307b\u306e\u304a\u306e\u30ad\u30d0",
                "Korean": "\ubd88\uaf43\uc5c4\ub2c8",
                "Spanish": "Colmillo \u00cdgneo"
            },
            "combat": {
                "energy": 6,
                "power": 8,
                "turns": 2,
                "buffs": null
            }
        }
    },
    "cinematicMoves": {
        "LEAF_STORM": {
            "id": "LEAF_STORM",
            "power": 130,
            "energy": -100,
            "durationMs": 2500,
            "type": {
                "type": "POKEMON_TYPE_GRASS",
                "names": {
                    "English": "Grass",
                    "German": "Pflanze",
                    "French": "Plante",
                    "Italian": "Erba",
                    "Japanese": "\u304f\u3055",
                    "Korean": "\ud480",
                    "Spanish": "Planta"
                }
            },
            "names": {
                "English": "Leaf Storm",
                "German": "Bl\u00e4ttersturm",
                "French": "Temp\u00eate Verte",
                "Italian": "Verdebufera",
                "Japanese": "\u30ea\u30fc\u30d5\u30b9\u30c8\u30fc\u30e0",
                "Korean": "\ub9ac\ud504\uc2a4\ud1b0",
                "Spanish": "Lluevehojas"
            },
            "combat": {
                "energy": -55,
                "power": 130,
                "turns": 1,
                "buffs": {
                    "activationChance": 100,
                    "attackerAttackStatsChange": -2,
                    "attackerDefenseStatsChange": null,
                    "targetAttackStatsChange": null,
                    "targetDefenseStatsChange": null
                }
            }
        },
        "GRASS_KNOT": {
            "id": "GRASS_KNOT",
            "power": 90,
            "energy": -50,
            "durationMs": 2500,
            "type": {
                "type": "POKEMON_TYPE_GRASS",
                "names": {
                    "English": "Grass",
                    "German": "Pflanze",
                    "French": "Plante",
                    "Italian": "Erba",
                    "Japanese": "\u304f\u3055",
                    "Korean": "\ud480",
                    "Spanish": "Planta"
                }
            },
            "names": {
                "English": "Grass Knot",
                "German": "Strauchler",
                "French": "N\u0153ud Herbe",
                "Italian": "Laccioerboso",
                "Japanese": "\u304f\u3055\u3080\u3059\u3073",
                "Korean": "\ud480\ubb36\uae30",
                "Spanish": "Hierba Lazo"
            },
            "combat": {
                "energy": -50,
                "power": 90,
                "turns": 1,
                "buffs": null
            }
        },
        "OVERHEAT": {
            "id": "OVERHEAT",
            "power": 160,
            "energy": -100,
            "durationMs": 4000,
            "type": {
                "type": "POKEMON_TYPE_FIRE",
                "names": {
                    "English": "Fire",
                    "German": "Feuer",
                    "French": "Feu",
                    "Italian": "Fuoco",
                    "Japanese": "\u307b\u306e\u304a",
                    "Korean": "\ubd88\uaf43",
                    "Spanish": "Fuego"
                }
            },
            "names": {
                "English": "Overheat",
                "German": "Hitzekoller",
                "French": "Surchauffe",
                "Italian": "Vampata",
                "Japanese": "\u30aa\u30fc\u30d0\u30fc\u30d2\u30fc\u30c8",
                "Korean": "\uc624\ubc84\ud788\ud2b8",
                "Spanish": "Sofoco"
            },
            "combat": {
                "energy": -55,
                "power": 130,
                "turns": 1,
                "buffs": {
                    "activationChance": 100,
                    "attackerAttackStatsChange": -2,
                    "attackerDefenseStatsChange": null,
                    "targetAttackStatsChange": null,
                    "targetDefenseStatsChange": null
                }
            }
        },
        "FLAMETHROWER": {
            "id": "FLAMETHROWER",
            "power": 65,
            "energy": -50,
            "durationMs": 2000,
            "type": {
                "type": "POKEMON_TYPE_FIRE",
                "names": {
                    "English": "Fire",
                    "German": "Feuer",
                    "French": "Feu",
                    "Italian": "Fuoco",
                    "Japanese": "\u307b\u306e\u304a",
                    "Korean": "\ubd88\uaf43",
                    "Spanish": "Fuego"
                }
            },
            "names": {
                "English": "Flamethrower",
                "German": "Flammenwurf",
                "French": "Lance-Flammes",
                "Italian": "Lanciafiamme",
                "Japanese": "\u304b\u3048\u3093\u307b\u3046\u3057\u3083",
                "Korean": "\ud654\uc5fc\ubc29\uc0ac",
                "Spanish": "Lanzallamas"
            },
            "combat": {
                "energy": -55,
                "power": 90,
                "turns": 1,
                "buffs": null
            }
        }
    },
    "eliteQuickMoves": [],
    "eliteCinematicMoves": [],
    "assets": null,
    "regionForms": [],
    "evolutions": [],
    "hasMegaEvolution": false,
    "megaEvolutions": [],
    "hasGigantamaxEvolution": false,
    "assetForms": []
}